  1           0 LOAD_BUILD_CLASS
              2 LOAD_CONST               0 (<code object SignUpView at 0x7f16f69416b0, file "/home/annie/django-ecommerce/django-ecommerce/test.py", line 1>)
              4 LOAD_CONST               1 ('SignUpView')
              6 MAKE_FUNCTION            0
              8 LOAD_CONST               1 ('SignUpView')
             10 LOAD_NAME                0 (View)
             12 CALL_FUNCTION            3
             14 STORE_NAME               1 (SignUpView)
             16 LOAD_CONST               2 (None)
             18 RETURN_VALUE

Disassembly of <code object SignUpView at 0x7f16f69416b0, file "/home/annie/django-ecommerce/django-ecommerce/test.py", line 1>:
  1           0 LOAD_NAME                0 (__name__)
              2 STORE_NAME               1 (__module__)
              4 LOAD_CONST               0 ('SignUpView')
              6 STORE_NAME               2 (__qualname__)

  2           8 LOAD_CONST               1 (<code object get at 0x7f16f69382a0, file "/home/annie/django-ecommerce/django-ecommerce/test.py", line 2>)
             10 LOAD_CONST               2 ('SignUpView.get')
             12 MAKE_FUNCTION            0
             14 STORE_NAME               3 (get)

  6          16 LOAD_CONST               3 (<code object post at 0x7f16f69389f0, file "/home/annie/django-ecommerce/django-ecommerce/test.py", line 6>)
             18 LOAD_CONST               4 ('SignUpView.post')
             20 MAKE_FUNCTION            0
             22 STORE_NAME               4 (post)
             24 LOAD_CONST               5 (None)
             26 RETURN_VALUE

Disassembly of <code object get at 0x7f16f69382a0, file "/home/annie/django-ecommerce/django-ecommerce/test.py", line 2>:
  3           0 LOAD_GLOBAL              0 (NewUserForm)
              2 STORE_FAST               3 (form)

  4           4 LOAD_GLOBAL              1 (render)
              6 LOAD_FAST                0 (self)
              8 LOAD_ATTR                2 (request)
             10 LOAD_CONST               1 ('account/signup.html')
             12 LOAD_CONST               2 ('form')
             14 LOAD_FAST                3 (form)
             16 BUILD_MAP                1
             18 LOAD_CONST               3 (('context',))
             20 CALL_FUNCTION_KW         3
             22 RETURN_VALUE

Disassembly of <code object post at 0x7f16f69389f0, file "/home/annie/django-ecommerce/django-ecommerce/test.py", line 6>:
  7           0 LOAD_GLOBAL              0 (NewUserForm)
              2 LOAD_FAST                0 (self)
              4 LOAD_ATTR                1 (request)
              6 LOAD_ATTR                2 (POST)
              8 JUMP_IF_TRUE_OR_POP     12
             10 LOAD_CONST               0 (None)
        >>   12 CALL_FUNCTION            1
             14 STORE_FAST               3 (form)

  8          16 LOAD_FAST                3 (form)
             18 LOAD_METHOD              3 (is_valid)
             20 CALL_METHOD              0
             22 POP_JUMP_IF_FALSE       84

  9          24 LOAD_FAST                3 (form)
             26 LOAD_ATTR                4 (cleaned_data)
             28 LOAD_METHOD              5 (get)
             30 LOAD_CONST               1 ('username')
             32 CALL_METHOD              1
             34 STORE_FAST               4 (username)

 10          36 LOAD_FAST                3 (form)
             38 LOAD_ATTR                4 (cleaned_data)
             40 LOAD_METHOD              5 (get)
             42 LOAD_CONST               2 ('password1')
             44 CALL_METHOD              1
             46 STORE_FAST               5 (password)

 11          48 LOAD_FAST                3 (form)
             50 LOAD_ATTR                4 (cleaned_data)
             52 LOAD_METHOD              5 (get)
             54 LOAD_CONST               3 ('email')
             56 CALL_METHOD              1
             58 STORE_FAST               6 (email)

 12          60 LOAD_GLOBAL              6 (User)
             62 LOAD_ATTR                7 (objects)
             64 LOAD_METHOD              8 (create_user)
             66 LOAD_FAST                4 (username)
             68 LOAD_FAST                6 (email)
             70 LOAD_FAST                5 (password)
             72 CALL_METHOD              3
             74 STORE_FAST               7 (user)

 13          76 LOAD_FAST                7 (user)
             78 LOAD_METHOD              9 (save)
             80 CALL_METHOD              0
             82 POP_TOP
        >>   84 LOAD_CONST               0 (None)
             86 RETURN_VALUE
